service_configuration_lib/__init__.py
service_configuration_lib/cached_view.py
service_configuration_lib/py.typed
service_configuration_lib/spark_config.py
service_configuration_lib/text_colors.py
service_configuration_lib/utils.py
service_configuration_lib/yaml_cached_view.py
service_configuration_lib-3.3.5.data/scripts/all_nodes_that_receive
service_configuration_lib-3.3.5.data/scripts/all_nodes_that_run
service_configuration_lib-3.3.5.data/scripts/dump_service_configuration_yaml
service_configuration_lib-3.3.5.data/scripts/services_deployed_here
service_configuration_lib-3.3.5.data/scripts/services_needing_puppet_help
service_configuration_lib-3.3.5.data/scripts/services_that_run_here
service_configuration_lib-3.3.5.dist-info/LICENSE
service_configuration_lib-3.3.5.dist-info/METADATA
service_configuration_lib-3.3.5.dist-info/WHEEL
service_configuration_lib-3.3.5.dist-info/top_level.txt
service_configuration_lib-3.3.5.dist-info/RECORD
