Metadata-Version: 2.1
Name: service-configuration-lib
Version: 3.3.5
Summary: Start, stop, and inspect Yelp SOA services
Home-page: https://github.com/Yelp/service_configuration_lib
Author: Yelp Compute Infrastructure Team
Author-email: opensource+scl@yelp.com
License: Copyright Yelp 2013, All Rights Reserved
Platform: UNKNOWN
Provides: service_configuration_lib
Requires-Dist: ephemeral-port-reserve>=1.1.0
Requires-Dist: PyYAML>=5.1
Requires-Dist: pyinotify
Requires-Dist: requests>=2.18.4
Requires-Dist: boto3
Provides-Extra: yelp
Requires-Dist: yelp-clog>=7; extra == "yelp"
